odoo/addons/auth_session_timeout_user_flag/__init__.py
odoo/addons/auth_session_timeout_user_flag/__manifest__.py
odoo/addons/auth_session_timeout_user_flag/data/res_users.xml
odoo/addons/auth_session_timeout_user_flag/i18n/ca_ES.po
odoo/addons/auth_session_timeout_user_flag/i18n/es.po
odoo/addons/auth_session_timeout_user_flag/models/__init__.py
odoo/addons/auth_session_timeout_user_flag/models/res_users.py
odoo/addons/auth_session_timeout_user_flag/views/res_users_views.xml
odoo12_addon_auth_session_timeout_user_flag-12.0.1.0.0.99.dev1.dist-info/METADATA
odoo12_addon_auth_session_timeout_user_flag-12.0.1.0.0.99.dev1.dist-info/WHEEL
odoo12_addon_auth_session_timeout_user_flag-12.0.1.0.0.99.dev1.dist-info/top_level.txt
odoo12_addon_auth_session_timeout_user_flag-12.0.1.0.0.99.dev1.dist-info/RECORD
