Metadata-Version: 2.1
Name: odoo12-addon-auth-session-timeout-user-flag
Version: 12.0.1.0.0.99.dev1
Summary: Terminate user's session after timeout only if they allow so with a user flag
Home-page: https://coopdevs.org
Author: Coopdevs Treball SCCL
License: AGPL-3
Platform: UNKNOWN
Classifier: Programming Language :: Python
Classifier: Framework :: Odoo
Classifier: License :: OSI Approved :: GNU Affero General Public License v3
Requires-Python: >=3.5
Requires-Dist: odoo12-addon-auth-session-timeout
Requires-Dist: odoo (<12.1dev,>=12.0a)
